odoo10_addon_account_invoice_kanban-10.0.1.1.0-py2.7-nspkg.pth
odoo/addons/account_invoice_kanban/README.rst
odoo/addons/account_invoice_kanban/__init__.py
odoo/addons/account_invoice_kanban/__manifest__.py
odoo/addons/account_invoice_kanban/demo/account_invoice_demo.xml
odoo/addons/account_invoice_kanban/i18n/account_invoice_kanban.pot
odoo/addons/account_invoice_kanban/i18n/am.po
odoo/addons/account_invoice_kanban/i18n/ar.po
odoo/addons/account_invoice_kanban/i18n/bg.po
odoo/addons/account_invoice_kanban/i18n/bs.po
odoo/addons/account_invoice_kanban/i18n/ca.po
odoo/addons/account_invoice_kanban/i18n/ca_ES.po
odoo/addons/account_invoice_kanban/i18n/cs.po
odoo/addons/account_invoice_kanban/i18n/da.po
odoo/addons/account_invoice_kanban/i18n/de.po
odoo/addons/account_invoice_kanban/i18n/el_GR.po
odoo/addons/account_invoice_kanban/i18n/en_GB.po
odoo/addons/account_invoice_kanban/i18n/es.po
odoo/addons/account_invoice_kanban/i18n/es_AR.po
odoo/addons/account_invoice_kanban/i18n/es_CL.po
odoo/addons/account_invoice_kanban/i18n/es_CO.po
odoo/addons/account_invoice_kanban/i18n/es_CR.po
odoo/addons/account_invoice_kanban/i18n/es_DO.po
odoo/addons/account_invoice_kanban/i18n/es_EC.po
odoo/addons/account_invoice_kanban/i18n/es_ES.po
odoo/addons/account_invoice_kanban/i18n/es_MX.po
odoo/addons/account_invoice_kanban/i18n/es_PE.po
odoo/addons/account_invoice_kanban/i18n/es_PY.po
odoo/addons/account_invoice_kanban/i18n/es_VE.po
odoo/addons/account_invoice_kanban/i18n/et.po
odoo/addons/account_invoice_kanban/i18n/eu.po
odoo/addons/account_invoice_kanban/i18n/fa.po
odoo/addons/account_invoice_kanban/i18n/fi.po
odoo/addons/account_invoice_kanban/i18n/fr.po
odoo/addons/account_invoice_kanban/i18n/fr_CA.po
odoo/addons/account_invoice_kanban/i18n/fr_CH.po
odoo/addons/account_invoice_kanban/i18n/gl.po
odoo/addons/account_invoice_kanban/i18n/gl_ES.po
odoo/addons/account_invoice_kanban/i18n/he.po
odoo/addons/account_invoice_kanban/i18n/hr.po
odoo10_addon_account_invoice_kanban-10.0.1.1.0.dist-info/DESCRIPTION.rst
odoo10_addon_account_invoice_kanban-10.0.1.1.0.dist-info/METADATA
odoo10_addon_account_invoice_kanban-10.0.1.1.0.dist-info/RECORD
odoo10_addon_account_invoice_kanban-10.0.1.1.0.dist-info/WHEEL
odoo10_addon_account_invoice_kanban-10.0.1.1.0.dist-info/metadata.json
odoo10_addon_account_invoice_kanban-10.0.1.1.0.dist-info/namespace_packages.txt
odoo10_addon_account_invoice_kanban-10.0.1.1.0.dist-info/top_level.txt
